educs/__init__.py
educs/color.py
educs/constants.py
educs/image.py
educs/math.py
educs/pygame_wrapper.py
educs-0.0.6.dist-info/WHEEL
educs-0.0.6.dist-info/METADATA
educs-0.0.6.dist-info/RECORD
