Metadata-Version: 2.1
Name: educs
Version: 0.0.6
Summary: A package wrapping pygame functionality in p5.js calling conventions. Used in computer science highschool course
Home-page: https://github.com/JBas/educs
License: MIT
Author: Joshua Bas
Author-email: joshua.n.bas@gmail.com
Requires-Python: >=3.8.0,<3.9
Classifier: License :: OSI Approved :: MIT License
Classifier: Programming Language :: Python :: 3
Classifier: Programming Language :: Python :: 3.8
Requires-Dist: multipledispatch (>=0.6.0,<0.7.0)
Requires-Dist: numpy (>=1.22.2,<2.0.0)
Requires-Dist: pygame (>=2.1.2,<3.0.0)
Project-URL: Repository, https://github.com/JBas/educs
